snek/__init__.py
snek/app.py
snek/cli.py
snek/config.py
snek/demo_ai.py
snek/game.py
snek/game_rules.py
snek/screens.py
snek/styles.css
snek/themes.py
snek/worlds.py
snek_tui-0.1.1.dist-info/METADATA
snek_tui-0.1.1.dist-info/WHEEL
snek_tui-0.1.1.dist-info/entry_points.txt
snek_tui-0.1.1.dist-info/licenses/LICENSE
snek_tui-0.1.1.dist-info/RECORD
